django_distinct_sum/__init__.py
django_distinct_sum/aggregates.py
django_distinct_sum-0.1.1.dist-info/LICENSE
django_distinct_sum-0.1.1.dist-info/METADATA
django_distinct_sum-0.1.1.dist-info/WHEEL
django_distinct_sum-0.1.1.dist-info/RECORD
